tsseg_eval/__init__.py
tsseg_eval/metrics.py
tsseg_eval-0.1.3.dist-info/LICENSE
tsseg_eval-0.1.3.dist-info/METADATA
tsseg_eval-0.1.3.dist-info/WHEEL
tsseg_eval-0.1.3.dist-info/top_level.txt
tsseg_eval-0.1.3.dist-info/RECORD
