Metadata-Version: 2.1
Name: tsseg-eval
Version: 0.1.3
Summary: Evaluation measures for time series segmentation
Home-page: https://github.com/fchavelli/tsseg-eval
Author: Félix Chavelli
Classifier: Programming Language :: Python :: 3
Classifier: License :: OSI Approved :: MIT License
Classifier: Operating System :: OS Independent
Requires-Python: >=3.6
License-File: LICENSE
Requires-Dist: numpy
Requires-Dist: scipy
Requires-Dist: scikit-learn
